feliz_db/__init__.py
feliz_db/mongo_tools.py
feliz_db/postgres_tools.py
feliz_db-0.2.3.dist-info/licenses/LICENSE
feliz_db-0.2.3.dist-info/METADATA
feliz_db-0.2.3.dist-info/WHEEL
feliz_db-0.2.3.dist-info/top_level.txt
feliz_db-0.2.3.dist-info/RECORD
