Metadata-Version: 2.4
Name: feliz_db
Version: 0.2.3
Summary: A framework designed to assist in using databases and compatible with feliz framework
Home-page: https://github.com/zenith3092/feliz_db
Author: Vincent Wu, Linga Chen, Brian Yin
Author-email: zenith3092@gmail.com
License: MIT
Project-URL: Source, https://github.com/zenith3092/feliz_db
Classifier: Programming Language :: Python :: 3
Classifier: License :: OSI Approved :: MIT License
Classifier: Operating System :: OS Independent
Requires-Python: >=3.9
License-File: LICENSE
Requires-Dist: psycopg2-binary
Requires-Dist: pymongo
Requires-Dist: mongoengine
Dynamic: author
Dynamic: author-email
Dynamic: classifier
Dynamic: description
Dynamic: description-content-type
Dynamic: home-page
Dynamic: license
Dynamic: license-file
Dynamic: project-url
Dynamic: requires-dist
Dynamic: requires-python
Dynamic: summary
